life.py
con-1.0.0.dist-info/DESCRIPTION.rst
con-1.0.0.dist-info/METADATA
con-1.0.0.dist-info/RECORD
con-1.0.0.dist-info/WHEEL
con-1.0.0.dist-info/entry_points.txt
con-1.0.0.dist-info/metadata.json
con-1.0.0.dist-info/top_level.txt
