Metadata-Version: 2.0
Name: con
Version: 1.0.0
Summary: Game of Line in Python 3
Home-page: https://github.com/nsgonultas/life
Author: Enes Gönültaş
Author-email: nsgonultas@gmail.com
License: UNKNOWN
Keywords: conway,life,game of life
Platform: UNKNOWN
